SeerPPO/RolloutBuffer.py
SeerPPO/__init__.py
SeerPPO/distribution.py
SeerPPO/past_models_download.py
SeerPPO/V1/__init__.py
SeerPPO/V1/bot.py
SeerPPO/V1/policy.py
SeerPPO/V2/__init__.py
SeerPPO/V2/action.py
SeerPPO/V2/bot.py
SeerPPO/V2/observation.py
SeerPPO/V2/policy.py
SeerPPO/V2/terminal.py
SeerPPO/V3/__init__.py
SeerPPO/V3/action.py
SeerPPO/V3/bot.py
SeerPPO/V3/observation.py
SeerPPO/V3/policy.py
SeerPPO/V3/terminal.py
SeerPPO/V4/__init__.py
SeerPPO/V4/action.py
SeerPPO/V4/bot.py
SeerPPO/V4/observation.py
SeerPPO/V4/policy.py
SeerPPO/V4/terminal.py
SeerPPO-0.0.61.dist-info/LICENSE
SeerPPO-0.0.61.dist-info/METADATA
SeerPPO-0.0.61.dist-info/WHEEL
SeerPPO-0.0.61.dist-info/top_level.txt
SeerPPO-0.0.61.dist-info/RECORD
